misis_elibrary.py
misis_elibrary-0.0.4.dist-info/LICENSE
misis_elibrary-0.0.4.dist-info/METADATA
misis_elibrary-0.0.4.dist-info/WHEEL
misis_elibrary-0.0.4.dist-info/entry_points.txt
misis_elibrary-0.0.4.dist-info/top_level.txt
misis_elibrary-0.0.4.dist-info/RECORD
