Metadata-Version: 2.1
Name: misis-elibrary
Version: 0.0.4
Summary: Программа для загрузки книг из электронной библиотеки МИСИС.
Home-page: https://github.com/Layerex/misis-elibrary
Author: Layerex
Author-email: layerex@dismail.de
Classifier: Programming Language :: Python :: 3
Classifier: License :: OSI Approved :: GNU General Public License v3 (GPLv3)
Classifier: Operating System :: OS Independent
Classifier: Topic :: Utilities
License-File: LICENSE
Requires-Dist: requests
Requires-Dist: img2pdf
Requires-Dist: beautifulsoup4
